pytoDus/__init__.py
pytoDus-0.0.1.dist-info/LICENSE
pytoDus-0.0.1.dist-info/METADATA
pytoDus-0.0.1.dist-info/WHEEL
pytoDus-0.0.1.dist-info/top_level.txt
pytoDus-0.0.1.dist-info/RECORD
